petrosa/__init__.py
petrosa/binance/binance.py
petrosa/checkers/consistency.py
petrosa/converters/.gitignore
petrosa/converters/__init__.py
petrosa/converters/backtests.py
petrosa/database/mongo.py
petrosa/database/sql.py
petrosa/messaging/kafkaproducer.py
petrosa/messaging/kafkareceiver.py
petrosa/messaging/pubsubproducer.py
petrosa/observability/opentel.py
petrosa/ta/__init__.py
petrosa/ta/strategies.py
petrosa/ta/utils.py
petrosa-0.0.67.dist-info/METADATA
petrosa-0.0.67.dist-info/WHEEL
petrosa-0.0.67.dist-info/licenses/LICENSE
petrosa-0.0.67.dist-info/RECORD
