Metadata-Version: 2.3
Name: petrosa
Version: 0.0.67
Summary: utilities for PETROSA
Project-URL: Homepage, https://github.com/PetroSa2/petrosa-apps
Project-URL: Bug Tracker, https://github.com/PetroSa2/petrosa-apps/issues
Author-email: "@yurisa2" <yuri@sa2.com.br>
License-File: LICENSE
Classifier: License :: OSI Approved :: MIT License
Classifier: Operating System :: OS Independent
Classifier: Programming Language :: Python :: 3
Requires-Python: >=3.7
Requires-Dist: google-cloud-pubsub
Requires-Dist: kafka-python
Requires-Dist: mysql-connector
Requires-Dist: opentelemetry-distro
Requires-Dist: opentelemetry-exporter-otlp
Requires-Dist: pandas
Requires-Dist: pymongo
Requires-Dist: requests
Requires-Dist: retry
